gears_clean_css
